MANIFEST.in
PKG-INFO
README.txt
ilrt.formalworkflow-configure.zcml
setup.cfg
setup.py
docs/HISTORY.txt
docs/INSTALL.txt
docs/LICENSE.GPL
docs/LICENSE.txt
docs/TODO.txt
docs/formalworkflow.png
ilrt/__init__.py
ilrt.formalworkflow.egg-info/PKG-INFO
ilrt.formalworkflow.egg-info/SOURCES.txt
ilrt.formalworkflow.egg-info/dependency_links.txt
ilrt.formalworkflow.egg-info/entry_points.txt
ilrt.formalworkflow.egg-info/namespace_packages.txt
ilrt.formalworkflow.egg-info/not-zip-safe
ilrt.formalworkflow.egg-info/paster_plugins.txt
ilrt.formalworkflow.egg-info/requires.txt
ilrt.formalworkflow.egg-info/top_level.txt
ilrt/formalworkflow/__init__.py
ilrt/formalworkflow/configure.zcml
ilrt/formalworkflow/profiles.zcml
ilrt/formalworkflow/setuphandlers.py
ilrt/formalworkflow/skins.zcml
ilrt/formalworkflow/version.txt
ilrt/formalworkflow/browser/README.txt
ilrt/formalworkflow/browser/__init__.py
ilrt/formalworkflow/browser/cancel.pt
ilrt/formalworkflow/browser/cancel.py
ilrt/formalworkflow/browser/checkin.pt
ilrt/formalworkflow/browser/checkin.py
ilrt/formalworkflow/browser/checkout.pt
ilrt/formalworkflow/browser/checkout.py
ilrt/formalworkflow/browser/configure.zcml
ilrt/formalworkflow/browser/info.py
ilrt/formalworkflow/browser/interfaces.py
ilrt/formalworkflow/profiles/default/actions.xml
ilrt/formalworkflow/profiles/default/contentrules.xml
ilrt/formalworkflow/profiles/default/ilrt.formalworkflow_various.txt
ilrt/formalworkflow/profiles/default/import_steps.xml
ilrt/formalworkflow/profiles/default/properties.xml
ilrt/formalworkflow/profiles/default/propertiestool.xml
ilrt/formalworkflow/profiles/default/repositorytool.xml
ilrt/formalworkflow/profiles/default/skins.xml
ilrt/formalworkflow/profiles/default/workflows.xml
ilrt/formalworkflow/profiles/default/workflows/formal_workflow/definition.xml
ilrt/formalworkflow/profiles/default/workflows/one_state_workflow/definition.xml
ilrt/formalworkflow/skins/formalworkflow/check_obj_permission.py
ilrt/formalworkflow/skins/formalworkflow/delete_confirmation.cpy
ilrt/formalworkflow/skins/formalworkflow/delete_confirmation.cpy.metadata
ilrt/formalworkflow/skins/formalworkflow/folder_copy.cpy
ilrt/formalworkflow/skins/formalworkflow/folder_copy.cpy.metadata
ilrt/formalworkflow/skins/formalworkflow/folder_paste.cpy
ilrt/formalworkflow/skins/formalworkflow/folder_paste.cpy.metadata
ilrt/formalworkflow/skins/formalworkflow/object_copy.cpy
