Metadata-Version: 1.1
Name: ilrt.formalworkflow
Version: 1.9
Summary: Formal workflow is designed to prevent editing, deletion or reversion of published content from skipping review
Home-page: http://bitbucket.org/edcrewe/ilrt.formalworkflow
Author: Internet Development, ILRT, University of Bristol
Author-email: internet-development@bris.ac.uk
License: GPL
Keywords: web zope plone workflow
Platform: UNKNOWN
Classifier: Programming Language :: Python
Classifier: Topic :: Software Development :: Libraries :: Python Modules
Classifier: Environment :: Web Environment
Classifier: Framework :: Plone
Classifier: Framework :: Zope2
Classifier: Framework :: Zope3
Classifier: Intended Audience :: Developers
Classifier: Intended Audience :: Other Audience
Classifier: License :: OSI Approved :: BSD License
Classifier: Operating System :: OS Independent
Classifier: Development Status :: 5 - Production/Stable
